streamlit-plotly-events/__init__.py
streamlit-plotly-events/frontend/build/asset-manifest.json
streamlit-plotly-events/frontend/build/bootstrap.min.css
streamlit-plotly-events/frontend/build/index.html
streamlit-plotly-events/frontend/build/precache-manifest.8e9b06a06bf75a898757510b52bdb797.js
streamlit-plotly-events/frontend/build/service-worker.js
streamlit-plotly-events/frontend/build/static/js/2.dfc85ffb.chunk.js
streamlit-plotly-events/frontend/build/static/js/2.dfc85ffb.chunk.js.LICENSE.txt
streamlit-plotly-events/frontend/build/static/js/2.dfc85ffb.chunk.js.map
streamlit-plotly-events/frontend/build/static/js/main.b6ac1491.chunk.js
streamlit-plotly-events/frontend/build/static/js/main.b6ac1491.chunk.js.map
streamlit-plotly-events/frontend/build/static/js/runtime-main.11ec9aca.js
streamlit-plotly-events/frontend/build/static/js/runtime-main.11ec9aca.js.map
streamlit_plotly_events/__init__.py
streamlit_plotly_events/test.py
streamlit_plotly_events/frontend/build/asset-manifest.json
streamlit_plotly_events/frontend/build/bootstrap.min.css
streamlit_plotly_events/frontend/build/index.html
streamlit_plotly_events/frontend/build/precache-manifest.8e9b06a06bf75a898757510b52bdb797.js
streamlit_plotly_events/frontend/build/precache-manifest.9b51c73e570ee97cd4890046c62db022.js
streamlit_plotly_events/frontend/build/service-worker.js
streamlit_plotly_events/frontend/build/static/js/2.10fcf98d.chunk.js
streamlit_plotly_events/frontend/build/static/js/2.10fcf98d.chunk.js.LICENSE.txt
streamlit_plotly_events/frontend/build/static/js/2.10fcf98d.chunk.js.map
streamlit_plotly_events/frontend/build/static/js/2.dfc85ffb.chunk.js
streamlit_plotly_events/frontend/build/static/js/2.dfc85ffb.chunk.js.LICENSE.txt
streamlit_plotly_events/frontend/build/static/js/2.dfc85ffb.chunk.js.map
streamlit_plotly_events/frontend/build/static/js/main.814c598c.chunk.js
streamlit_plotly_events/frontend/build/static/js/main.814c598c.chunk.js.map
streamlit_plotly_events-0.0.6.dist-info/LICENSE
streamlit_plotly_events-0.0.6.dist-info/METADATA
streamlit_plotly_events-0.0.6.dist-info/WHEEL
streamlit_plotly_events-0.0.6.dist-info/top_level.txt
streamlit_plotly_events-0.0.6.dist-info/RECORD
