Metadata-Version: 2.1
Name: streamlit-plotly-events
Version: 0.0.6
Summary: Plotly chart component for Streamlit that also allows for events to bubble back up to Streamlit.
Home-page: https://github.com/null-jones/streamlit-plotly-events
Author: Ellie Jones
Author-email: ellie@altaml.com
License: UNKNOWN
Platform: UNKNOWN
Requires-Python: >=3.6
